{"module":"Erp","models":[{"name":"Client","softDelete":true,"timestamp":true,"properties":[{"name":"clientType","type":"Enum","ref":"","refDisplayField":"","enumOptions":"EMPRESA|PERSONA","label":"","icon":"category","required":true,"disabled":false,"unique":false,"default":"","search":false,"i18n":{"en":"Type","es":"Tipo","pt":"Tipo"}},{"name":"name","type":"String","ref":"","refDisplayField":"","enumOptions":"","label":"","icon":"badge","required":false,"search":false,"disabled":false,"unique":false,"i18n":{"en":"Social Reason","es":"Razon Social","pt":"Social Reason"}},{"name":"cuit","type":"String","ref":"","refDisplayField":"","enumOptions":"","label":"","icon":"fingerprint","required":false,"search":false,"disabled":false,"unique":false,"i18n":{"en":"Identification ","es":"CUIT / CUIL","pt":"Identification "}},{"name":"address","type":"String","ref":"","refDisplayField":"","enumOptions":"","label":"","icon":"pin_drop","required":false,"search":true,"disabled":false,"unique":false,"i18n":{"en":"Address","es":"Dirección","pt":"Dirección"}},{"name":"mainContact","type":"String","ref":"","refDisplayField":"","enumOptions":"","label":"","icon":"perm_contact_calendar","required":false,"search":false,"disabled":false,"unique":false,"i18n":{"en":"Main Contact","es":"Contacto Principal","pt":"Contacto Principal"}},{"name":"mainPhone","type":"String","ref":"","refDisplayField":"","enumOptions":"","label":"","icon":"phone","required":false,"search":false,"disabled":false,"unique":false,"i18n":{"en":"Main Phone","es":"Teléfono Principal","pt":"Teléfono Principal"}},{"name":"mainMail","type":"String","ref":"","refDisplayField":"","enumOptions":"","label":"","icon":"email","required":false,"search":false,"disabled":false,"unique":false,"i18n":{"en":"Main Email","es":"Email Principal","pt":"Email Principal"}}]},{"name":"Warehouse","softDelete":false,"timestamp":true,"properties":[{"name":"name","type":"String","ref":"","refDisplayField":"","enumOptions":"","label":"","icon":"house_siding","required":true,"disabled":false,"unique":true,"default":"","search":true,"i18n":{"en":"Name","es":"Nombre","pt":"Nome"}},{"name":"address","type":"String","ref":"","refDisplayField":"","enumOptions":"","label":"","icon":"location_on","required":false,"search":true,"disabled":false,"unique":false,"i18n":{"en":"Address","es":"Dirección","pt":"direção"}}]},{"name":"StockDevice","softDelete":false,"timestamp":true,"properties":[{"name":"brand","type":"ObjectId","ref":"Brand","refDisplayField":"name","enumOptions":"","label":"","icon":"star_border_purple500","required":false,"search":false,"disabled":false,"unique":false,"i18n":{"en":"Brand","es":"Marca","pt":"Marca"}},{"name":"brandModel","type":"ObjectId","ref":"BrandModel","refDisplayField":"name","enumOptions":"","label":"","icon":"model_training","required":false,"search":true,"disabled":false,"unique":false,"i18n":{"en":"Model","es":"Modelo","pt":"Modelo"}},{"name":"warehouse","type":"ObjectId","ref":"Warehouse","refDisplayField":"name","enumOptions":"","label":"","icon":"house_siding","required":false,"search":false,"disabled":false,"unique":false,"i18n":{"en":"Warehouse","es":"Deposito","pt":"Armazém"}},{"name":"serial","type":"String","ref":"","refDisplayField":"","enumOptions":"","label":"","icon":"fingerprint","required":true,"search":true,"disabled":false,"unique":true,"i18n":{"en":"Serial Number","es":"Numero de Serie","pt":"Número de série"}},{"name":"expirationDate","type":"Date","ref":"","refDisplayField":"","enumOptions":"","label":"","icon":"event","required":false,"search":false,"disabled":false,"unique":false,"i18n":{"en":"Expiration Date","es":"Fecha de Vencimiento","pt":"Expiration Date"}},{"name":"client","type":"ObjectId","ref":"Client","refDisplayField":"name","enumOptions":"","label":"","icon":"person","required":false,"disabled":false,"unique":false,"default":"","search":false,"i18n":{"en":"Client","es":"Cliente","pt":"Cliente"}},{"name":"clientBranch","type":"ObjectId","ref":"Client.branches","refDisplayField":"name","enumOptions":"","label":"","icon":"store","required":false,"disabled":false,"unique":false,"default":"","search":false,"i18n":{"en":"Client","es":"Cliente","pt":"Cliente"}}]},{"name":"StockItem","softDelete":false,"timestamp":true,"properties":[{"name":"name","type":"String","ref":"Brand","refDisplayField":"name","enumOptions":"","label":"","icon":"short_text","required":true,"search":true,"disabled":false,"unique":false,"i18n":{"en":"Name","es":"Nombre","pt":"Nome"}},{"name":"warehouse","type":"ObjectId","ref":"Warehouse","refDisplayField":"name","enumOptions":"","label":"","icon":"house_siding","required":false,"search":false,"disabled":false,"unique":false,"i18n":{"en":"Warehouse","es":"Deposito","pt":"Armazém"}},{"name":"batch","type":"String","ref":"","refDisplayField":"","enumOptions":"","label":"","icon":"ballot","required":false,"search":true,"disabled":false,"unique":false,"i18n":{"en":"Batch","es":"Lote","pt":"Lote"}},{"name":"initialQuantity","type":"Int","ref":"","refDisplayField":"","enumOptions":"","label":"","icon":"numbers","required":false,"search":false,"disabled":false,"unique":false,"i18n":{"en":"Initial Quantity","es":"Cantidad Inicial","pt":"Initial Quantity"}},{"name":"currentQuantity","type":"Int","ref":"","refDisplayField":"","enumOptions":"","label":"","icon":"numbers","required":false,"search":false,"disabled":false,"unique":false,"i18n":{"en":"Current Quantity","es":"Cantidad actual","pt":"currentQuantity"}},{"name":"expirationDate","type":"Date","ref":"","refDisplayField":"","enumOptions":"","label":"","icon":"event","required":false,"search":false,"disabled":false,"unique":false,"i18n":{"en":"Expiration Date","es":"Fecha de Vencimiento","pt":"Expiration Date"}}]},{"name":"Brand","softDelete":true,"timestamp":true,"properties":[{"name":"name","type":"String","ref":"","refDisplayField":"","enumOptions":"","label":"","icon":"aod_tablet","required":true,"disabled":false,"unique":true,"default":"","search":true,"i18n":{"en":"Name","es":"Nombre","pt":"Nome"}}]},{"name":"BrandModel","softDelete":true,"timestamp":true,"properties":[{"name":"brand","type":"ObjectId","ref":"Brand","refDisplayField":"name","enumOptions":"","label":"","icon":"store","required":false,"search":false,"disabled":false,"unique":false,"i18n":{"en":"Brand","es":"Marca","pt":"Marca"}},{"name":"name","type":"String","ref":"","refDisplayField":"","enumOptions":"","label":"","icon":"aod_tablet","required":true,"search":true,"disabled":false,"unique":false,"i18n":{"en":"Model","es":"Modelo","pt":"Modelo"}}]},{"name":"SaleOrder","softDelete":false,"timestamp":true,"properties":[{"name":"number","type":"Int","ref":"","refDisplayField":"","enumOptions":"","label":"","icon":"numbers","required":true,"disabled":false,"unique":true,"default":"","search":true,"i18n":{"en":"Number","es":"Número","pt":"Numero"}},{"name":"client","type":"ObjectId","ref":"Client","refDisplayField":"name","enumOptions":"","label":"","icon":"account_box","required":true,"search":false,"disabled":false,"unique":false,"i18n":{"en":"Client","es":"Cliente","pt":"Cliente"}},{"name":"date","type":"Date","ref":"","refDisplayField":"","enumOptions":"","label":"","icon":"today","required":true,"search":false,"disabled":false,"unique":false,"i18n":{"en":"Date","es":"Fecha","pt":"Fecha"}},{"name":"expirationDate","type":"Date","ref":"","refDisplayField":"","enumOptions":"","label":"","icon":"event","required":false,"search":false,"disabled":false,"unique":false,"i18n":{"en":"Expiration Date","es":"Fecha de vencimiento","pt":"Fecha de vencimiento"}},{"name":"status","type":"Enum","ref":"","refDisplayField":"","enumOptions":"DRAFT|APPROVED|CANCELED|CLOSED","label":"","icon":"assignment_turned_in","required":false,"search":false,"disabled":false,"unique":false,"i18n":{"en":"Status","es":"Estado","pt":"Estado"}},{"name":"total","type":"Float","ref":"","refDisplayField":"","enumOptions":"","label":"","icon":"paid","required":false,"search":false,"disabled":false,"unique":false,"i18n":{"en":"Total","es":"Total","pt":"Total"}}]},{"name":"ServiceOffered","softDelete":false,"timestamp":false,"properties":[{"name":"name","type":"String","ref":"","refDisplayField":"","enumOptions":"","label":"","icon":"short_text","required":true,"disabled":false,"unique":true,"default":"","search":true,"i18n":{"en":"Name","es":"Nombre","pt":"Nome"}},{"name":"description","type":"StringLarge","ref":"","refDisplayField":"","enumOptions":"","label":"","icon":"description","required":false,"search":true,"disabled":false,"unique":false,"i18n":{"en":"Description","es":"Descripción","pt":"Description"}},{"name":"price","type":"Float","ref":"","refDisplayField":"","enumOptions":"","label":"","icon":"paid","required":false,"search":false,"disabled":false,"unique":false,"i18n":{"en":"Price","es":"Precio","pt":"Precio"}}]}]}